guit/__init__.py
guit/cli.py
guit/constants.py
guit/utils.py
guit-0.1.0.dist-info/entry_points.txt
guit-0.1.0.dist-info/LICENSE
guit-0.1.0.dist-info/WHEEL
guit-0.1.0.dist-info/METADATA
guit-0.1.0.dist-info/RECORD
