Metadata-Version: 2.1
Name: guit
Version: 0.1.0
Summary: A Python CLI to open a web page from a Git repository.
Home-page: https://github.com/joaopalmeiro/guit
License: MIT
Keywords: guit,cli,git,browser,github,gitlab
Author: João Palmeiro
Author-email: joaommpalmeiro@gmail.com
Requires-Python: >=3.6,<4.0
Classifier: Development Status :: 3 - Alpha
Classifier: Environment :: Console
Classifier: Intended Audience :: Developers
Classifier: Intended Audience :: Information Technology
Classifier: Intended Audience :: Science/Research
Classifier: License :: OSI Approved :: MIT License
Classifier: Natural Language :: English
Classifier: Operating System :: OS Independent
Classifier: Programming Language :: Python :: 3
Classifier: Programming Language :: Python :: 3.6
Classifier: Programming Language :: Python :: 3.7
Classifier: Programming Language :: Python :: 3.8
Classifier: Programming Language :: Python :: 3.9
Classifier: Programming Language :: Python :: Implementation :: CPython
Classifier: Topic :: Terminals
Classifier: Topic :: Utilities
Requires-Dist: click (>=7.1.2,<8.0.0)
Requires-Dist: importlib-metadata (>=1.0,<2.0); python_version < "3.8"
Requires-Dist: parse (>=1.19.0,<2.0.0)
Requires-Dist: sh (>=1.14.2,<2.0.0)
Project-URL: Bug Tracker, https://github.com/joaopalmeiro/guit/issues
Project-URL: Repository, https://github.com/joaopalmeiro/guit
Project-URL: Twitter, https://twitter.com/joaompalmeiro
